{
    "id": "e7a36486-796f-45e5-b961-c322128a4385",
    "id_proprietario": "7772dd1c-e416-4d06-abed-850ebc5fbc6b",
    "oggetti": [
        {
            "id": "843ccd37-42f2-42b3-9a61-5e46c674a089",
            "nome": "Pozione Rossa",
            "usato": false,
            "valore": 30,
            "tipo_oggetto": "Ristorativo",
            "classe": "PozioneCura"
        },
        {
            "id": "b49eaf81-6f4a-4639-b180-6c9db64dfd96",
            "nome": "Pozione Rossa",
            "usato": false,
            "valore": 30,
            "tipo_oggetto": "Ristorativo",
            "classe": "PozioneCura"
        },
        {
            "id": "49cbd4ab-aa7f-48de-8aa4-ef047975bc1b",
            "nome": "Medaglione",
            "usato": false,
            "valore": 10,
            "tipo_oggetto": "Buff",
            "classe": "Medaglione"
        },
        {
            "id": "6d1319bb-24ae-43ff-9d8c-692082c06702",
            "nome": "Pozione Rossa",
            "usato": false,
            "valore": 30,
            "tipo_oggetto": "Ristorativo",
            "classe": "PozioneCura"
        },
        {
            "id": "38968095-ebf2-42d1-bb44-28be37301e46",
            "nome": "Pozione Rossa",
            "usato": false,
            "valore": 30,
            "tipo_oggetto": "Ristorativo",
            "classe": "PozioneCura"
        },
        {
            "id": "6170c2ae-879f-4225-8de9-3c62105d6fa7",
            "nome": "Bomba Acida",
            "usato": false,
            "valore": 30,
            "tipo_oggetto": "Offensivo",
            "classe": "BombaAcida"
        },
        {
            "id": "78d51c4d-8048-4e1d-9cf4-1d1ea38fc1cc",
            "nome": "Pozione Rossa",
            "usato": false,
            "valore": 30,
            "tipo_oggetto": "Ristorativo",
            "classe": "PozioneCura"
        },
        {
            "id": "e462af64-7dbf-4cf8-b9de-11ddc96fe918",
            "nome": "Bomba Acida",
            "usato": false,
            "valore": 30,
            "tipo_oggetto": "Offensivo",
            "classe": "BombaAcida"
        },
        {
            "id": "f1d73ede-98c0-4708-bb58-e24c43f850c7",
            "nome": "Pozione Rossa",
            "usato": false,
            "valore": 30,
            "tipo_oggetto": "Ristorativo",
            "classe": "PozioneCura"
        },
        {
            "id": "84f8567e-f6a3-4061-a094-6c619c4f12d2",
            "nome": "Pozione Rossa",
            "usato": false,
            "valore": 30,
            "tipo_oggetto": "Ristorativo",
            "classe": "PozioneCura"
        },
        {
            "id": "d6c3f7e4-08a6-4484-9d01-c6b6708ec674",
            "nome": "Bomba Acida",
            "usato": false,
            "valore": 30,
            "tipo_oggetto": "Offensivo",
            "classe": "BombaAcida"
        },
        {
            "id": "0cd3563b-6bdf-4b7b-8f58-3905ae96aa24",
            "nome": "Pozione Rossa",
            "usato": false,
            "valore": 30,
            "tipo_oggetto": "Ristorativo",
            "classe": "PozioneCura"
        },
        {
            "id": "d3881b61-814b-4465-99ac-147d4b2730bd",
            "nome": "Pozione Rossa",
            "usato": false,
            "valore": 30,
            "tipo_oggetto": "Ristorativo",
            "classe": "PozioneCura"
        },
        {
            "id": "ae4a5032-7d53-4db0-b127-37dad01935b1",
            "nome": "Bomba Acida",
            "usato": false,
            "valore": 30,
            "tipo_oggetto": "Offensivo",
            "classe": "BombaAcida"
        },
        {
            "id": "4e34b7a1-db53-4b55-84ef-e8898f2c9579",
            "nome": "Pozione Rossa",
            "usato": false,
            "valore": 30,
            "tipo_oggetto": "Ristorativo",
            "classe": "PozioneCura"
        },
        {
            "id": "70de750e-c875-4d2f-a33b-b98b15426074",
            "nome": "Pozione Rossa",
            "usato": false,
            "valore": 30,
            "tipo_oggetto": "Ristorativo",
            "classe": "PozioneCura"
        },
        {
            "id": "2cbf1292-153d-4d2f-8881-550dda1f56a9",
            "nome": "Bomba Acida",
            "usato": false,
            "valore": 30,
            "tipo_oggetto": "Offensivo",
            "classe": "BombaAcida"
        }
    ]
}